rayou/cdk_url_shortener/__init__.py
rayou/cdk_url_shortener/py.typed
rayou/cdk_url_shortener/_jsii/__init__.py
rayou/cdk_url_shortener/_jsii/cdk-url-shortener@0.1.2.jsii.tgz
rayou.cdk_url_shortener-0.1.2.dist-info/METADATA
rayou.cdk_url_shortener-0.1.2.dist-info/WHEEL
rayou.cdk_url_shortener-0.1.2.dist-info/top_level.txt
rayou.cdk_url_shortener-0.1.2.dist-info/RECORD
