Metadata-Version: 2.1
Name: rayou.cdk-url-shortener
Version: 0.1.2
Summary: Deploy a URL shortener with custom domain support in just a few lines of code.
Home-page: https://github.com/rayou/cdk-url-shortener.git
Author: Ray Ou<yuhung.ou@live.com>
License: Apache-2.0
Project-URL: Source, https://github.com/rayou/cdk-url-shortener.git
Platform: UNKNOWN
Classifier: Intended Audience :: Developers
Classifier: Operating System :: OS Independent
Classifier: Programming Language :: JavaScript
Classifier: Programming Language :: Python :: 3 :: Only
Classifier: Programming Language :: Python :: 3.6
Classifier: Programming Language :: Python :: 3.7
Classifier: Programming Language :: Python :: 3.8
Classifier: Typing :: Typed
Classifier: Development Status :: 4 - Beta
Classifier: License :: OSI Approved
Requires-Python: >=3.6
Requires-Dist: aws-cdk.aws-apigateway (<2.0.0,>=1.61.0)
Requires-Dist: aws-cdk.aws-certificatemanager (<2.0.0,>=1.61.0)
Requires-Dist: aws-cdk.aws-dynamodb (<2.0.0,>=1.61.0)
Requires-Dist: aws-cdk.aws-iam (<2.0.0,>=1.61.0)
Requires-Dist: aws-cdk.aws-lambda-event-sources (<2.0.0,>=1.61.0)
Requires-Dist: aws-cdk.aws-lambda (<2.0.0,>=1.61.0)
Requires-Dist: aws-cdk.aws-route53-targets (<2.0.0,>=1.61.0)
Requires-Dist: aws-cdk.aws-route53 (<2.0.0,>=1.61.0)
Requires-Dist: aws-cdk.core (<2.0.0,>=1.61.0)
Requires-Dist: constructs (<4.0.0,>=3.0.4)
Requires-Dist: jsii (<2.0.0,>=1.12.0)
Requires-Dist: publication (>=0.0.3)
